LICENSE
MANIFEST.in
README.rst
setup.py
django_lazydrf.egg-info/PKG-INFO
django_lazydrf.egg-info/SOURCES.txt
django_lazydrf.egg-info/dependency_links.txt
django_lazydrf.egg-info/requires.txt
django_lazydrf.egg-info/top_level.txt
lazydrf/__init__.py
lazydrf/apps.py
lazydrf/models.py
lazydrf/tests.py
lazydrf/utils.py
lazydrf/migrations/__init__.py