Metadata-Version: 1.1
Name: django-lazydrf
Version: 0.0.1
Summary: Dirty magic to generate automated DRF endpoints
Home-page: https://github.com/vst/django-lazydrf
Author: Vehbi Sinan Tunalioglu
Author-email: vst@vsthost.com
License: BSD License
Platform: UNKNOWN
Classifier: Environment :: Web Environment
Classifier: Framework :: Django
Classifier: Framework :: Django :: 1.9
Classifier: Intended Audience :: Developers
Classifier: License :: OSI Approved :: BSD License
Classifier: Operating System :: OS Independent
Classifier: Programming Language :: Python
Classifier: Programming Language :: Python :: 3
Classifier: Programming Language :: Python :: 3.4
Classifier: Programming Language :: Python :: 3.5
Classifier: Topic :: Internet :: WWW/HTTP
Classifier: Topic :: Internet :: WWW/HTTP :: Dynamic Content
